python_xlsxio-0.1.5.dist-info/WHEEL
python_xlsxio-0.1.5.dist-info/RECORD
python_xlsxio-0.1.5.dist-info/METADATA
python_xlsxio-0.1.5.dist-info/top_level.txt
python_xlsxio-0.1.5.dist-info/LICENSE
xlsxio/__init__.pyi
xlsxio/__init__.py
xlsxio/_xlsxio.cpython-39-x86_64-linux-gnu.so
