Metadata-Version: 2.1
Name: python-xlsxio
Version: 0.1.5
Summary: Wrapper xlsxio library for python
Home-page: https://github.com/Chiorufarewerin/python-xlsxio
Author: Artur Beltsov
Author-email: artur1998g@gmail.com
License: MIT
Project-URL: GitHub, https://github.com/Chiorufarewerin/python-xlsxio
Keywords: xlsxio,python,c,excel,read
Platform: UNKNOWN
Classifier: Development Status :: 3 - Alpha
Classifier: License :: OSI Approved :: MIT License
Classifier: Programming Language :: Cython
Classifier: Programming Language :: Python
Classifier: Programming Language :: Python :: 3
Classifier: Programming Language :: Python :: 3.7
Classifier: Programming Language :: Python :: 3.8
Classifier: Programming Language :: Python :: 3.9
Classifier: Programming Language :: Python :: 3.10
Classifier: Programming Language :: Python :: 3 :: Only
Classifier: Operating System :: Microsoft :: Windows
Classifier: Operating System :: MacOS
Classifier: Operating System :: Unix
Requires-Python: >=3.7
